{
  "Interactions": {
    "Wielding": "Double_Jump",
    "Primary": {
      "Settings": {
        "Adventure": {
          "Cooldown": {
            "Id": "BlockInteraction",
            "Cooldown": 0.35
          }
        },
        "Creative": {
          "AllowSkipChainOnClick": true,
          "Cooldown": {
            "Id": "BlockInteraction_Creative",
            "Cooldown": 0.35,
            "ClickBypass": true
          }
        }
      },
      "Interactions": [
        {
          "Type": "Simple",
          "Next": {
            "Type": "UseBlock",
            "Failed": "Unarmed_Attack"
          }
        }
      ]
    },
    "Use": {
      "Settings": {
        "Adventure": {
          "Cooldown": {
            "Id": "BlockInteraction",
            "Cooldown": 0.35
          }
        },
        "Creative": {
          "Cooldown": {
            "Id": "BlockInteraction_Creative",
            "Cooldown": 0.35,
            "ClickBypass": true
          }
        }
      },
      "Interactions": [
        {
          "Type": "Simple",
          "Effects": {
            "ItemAnimationId": "Interact"
          },
          "Next": {
            "Type": "UseBlock",
            "Failed": {
              "Type": "UseEntity",
              "Failed": {
                "Type": "BreakBlock",
                "Harvest": true
              }
            }
          }
        }
      ]
    },
    "Pick": {
      "Settings": {
        "Adventure": {
          "Cooldown": {
            "Id": "BlockInteraction",
            "Cooldown": 0.35
          }
        },
        "Creative": {
          "Cooldown": {
            "Id": "BlockInteraction_Creative",
            "Cooldown": 0.35,
            "ClickBypass": true
          }
        }
      },
      "Interactions": [
        {
          "Type": "Simple",
          "Effects": {
            "ItemAnimationId": "Interact"
          },
          "Next": {
            "Type": "PickBlock"
          }
        }
      ]
    },
    "Secondary": {
      "Interactions": [
        "Yht_QuickerStacker_QuickStackToChest"
      ],
      "Cooldown": {
        "Id": "Yht_QuickerStacker_QuickStack",
        "Cooldown": 0.25
      },
      "RequireNewClick": false
    }
  }
}
